.travis.yml
CHANGES.rst
README.rst
development.ini
setup.cfg
setup.py
docs/images/options.png
docs/images/settings.png
kotti_grid/__init__.py
kotti_grid/fanstatic.py
kotti_grid/populate.py
kotti_grid/utils.py
kotti_grid/views.py
kotti_grid/widget.py
kotti_grid.egg-info/PKG-INFO
kotti_grid.egg-info/SOURCES.txt
kotti_grid.egg-info/dependency_links.txt
kotti_grid.egg-info/entry_points.txt
kotti_grid.egg-info/not-zip-safe
kotti_grid.egg-info/requires.txt
kotti_grid.egg-info/top_level.txt
kotti_grid/locale/README
kotti_grid/locale/kotti_grid.pot
kotti_grid/locale/de/LC_MESSAGES/kotti_grid.mo
kotti_grid/locale/de/LC_MESSAGES/kotti_grid.po
kotti_grid/locale/en/LC_MESSAGES/kotti_grid.mo
kotti_grid/locale/en/LC_MESSAGES/kotti_grid.po
kotti_grid/static/css/style.css
kotti_grid/static/css/style.min.css
kotti_grid/static/img/README
kotti_grid/static/js/script.js
kotti_grid/static/js/script.min.js
kotti_grid/templates/add-tile.pt
kotti_grid/templates/browser.pt
kotti_grid/templates/grid.pt
kotti_grid/templates/tile-view.pt
kotti_grid/tests/conftest.py
kotti_grid/tests/test_configure.py
kotti_grid/tests/test_functional.py
kotti_grid/tests/test_utils.py
kotti_grid/tests/test_views.py
kotti_grid/tests/test_widget.py